{"note":"Don't delete this file! It's used internally to help with page regeneration.","body":"To get started right away with TextMate 2, you can download a perfectly free binary build from [here](https://github.com/jwhitehorn/textmate/downloads).\r\n\r\nOr, [click here](https://github.com/jwhitehorn/textmate/wiki/building) for instructions on how to compile it.\r\n\r\n![textmate](https://raw.github.com/jwhitehorn/textmate/master/textmate.png)\r\n\r\n## Modifications & Licensing\r\n\r\nThe GPL sucks.\r\n\r\nAllan Odgaard released TextMate under this horrible license, but wants any modifications given to him as \"public domain\" so he doesn't have to be burdened by the same restrictions the not-free-as-in-speech GPL provides. To which, I say:\r\n\r\nAny modifications in this branch are released under the SAME GPL license.","name":"Textmate (forked)","google":"","tagline":"TextMate 2 is a free graphical text editor for Mac OS X"}